{
  "$schema": "https://schema.management.azure.com/schemas/2019-04-01/deploymentTemplate.json#",
  "contentVersion": "1.0.0.0",
  "metadata": {
    "_generator": {
      "name": "bicep",
      "version": "0.41.2.15936",
      "templateHash": "15324252364204715281"
    }
  },
  "parameters": {
    "location": {
      "type": "string",
      "defaultValue": "[resourceGroup().location]",
      "metadata": {
        "description": "Azure region for all resources."
      }
    },
    "staticWebAppLocation": {
      "type": "string",
      "defaultValue": "[parameters('location')]",
      "metadata": {
        "description": "Azure region for the Static Web App. Defaults to the main deployment location."
      }
    },
    "staticWebAppName": {
      "type": "string",
      "metadata": {
        "description": "Static Web App name."
      }
    },
    "webAppName": {
      "type": "string",
      "metadata": {
        "description": "Web App name."
      }
    },
    "appServicePlanName": {
      "type": "string",
      "defaultValue": "[format('{0}-plan', parameters('webAppName'))]",
      "metadata": {
        "description": "App Service plan name for the Web App."
      }
    },
    "applicationInsightsName": {
      "type": "string",
      "defaultValue": "[format('{0}-appi', parameters('webAppName'))]",
      "metadata": {
        "description": "Application Insights name."
      }
    },
    "keyVaultName": {
      "type": "string",
      "metadata": {
        "description": "Key Vault name."
      }
    },
    "sqlServerName": {
      "type": "string",
      "metadata": {
        "description": "SQL Server name."
      }
    },
    "sqlDatabaseName": {
      "type": "string",
      "metadata": {
        "description": "SQL Database name."
      }
    },
    "sqlAdministratorLogin": {
      "type": "string",
      "metadata": {
        "description": "SQL administrator login."
      }
    },
    "sqlAdministratorPassword": {
      "type": "securestring",
      "metadata": {
        "description": "SQL administrator password."
      }
    },
    "jwtSecret": {
      "type": "securestring",
      "metadata": {
        "description": "JWT secret key."
      }
    },
    "jwtIssuer": {
      "type": "string",
      "defaultValue": "kinhub",
      "metadata": {
        "description": "JWT issuer."
      }
    },
    "jwtAccessTokenExpiryMinutes": {
      "type": "string",
      "defaultValue": "15",
      "metadata": {
        "description": "JWT access token expiry in minutes."
      }
    },
    "businessTimeZoneId": {
      "type": "string",
      "defaultValue": "Europe/Rome",
      "metadata": {
        "description": "Business timezone identifier."
      }
    }
  },
  "variables": {
    "sqlServerFullyQualifiedDomainName": "[format('{0}{1}', parameters('sqlServerName'), environment().suffixes.sqlServerHostname)]",
    "sqlConnectionString": "[format('Server=tcp:{0},1433;Initial Catalog={1};Persist Security Info=False;User ID={2};Password={3};MultipleActiveResultSets=False;Encrypt=True;TrustServerCertificate=False;Connection Timeout=30;', variables('sqlServerFullyQualifiedDomainName'), parameters('sqlDatabaseName'), parameters('sqlAdministratorLogin'), parameters('sqlAdministratorPassword'))]",
    "sqlConnectionStringSecretName": "sql-connection-string",
    "jwtSecretSecretName": "jwt-secret",
    "keyVaultSecretsUserRoleDefinitionId": "[subscriptionResourceId('Microsoft.Authorization/roleDefinitions', '4633458b-17de-408a-b874-0445c86b69e6')]"
  },
  "resources": [
    {
      "type": "Microsoft.Insights/components",
      "apiVersion": "2020-02-02",
      "name": "[parameters('applicationInsightsName')]",
      "location": "[parameters('location')]",
      "kind": "web",
      "properties": {
        "Application_Type": "web",
        "WorkspaceResourceId": null
      }
    },
    {
      "type": "Microsoft.KeyVault/vaults",
      "apiVersion": "2023-07-01",
      "name": "[parameters('keyVaultName')]",
      "location": "[parameters('location')]",
      "properties": {
        "enablePurgeProtection": true,
        "enableRbacAuthorization": true,
        "enabledForDeployment": false,
        "enabledForDiskEncryption": false,
        "enabledForTemplateDeployment": false,
        "publicNetworkAccess": "Enabled",
        "sku": {
          "family": "A",
          "name": "standard"
        },
        "softDeleteRetentionInDays": 90,
        "tenantId": "[tenant().tenantId]"
      }
    },
    {
      "type": "Microsoft.Sql/servers",
      "apiVersion": "2023-08-01-preview",
      "name": "[parameters('sqlServerName')]",
      "location": "[parameters('location')]",
      "properties": {
        "administratorLogin": "[parameters('sqlAdministratorLogin')]",
        "administratorLoginPassword": "[parameters('sqlAdministratorPassword')]",
        "publicNetworkAccess": "Enabled",
        "version": "12.0"
      }
    },
    {
      "type": "Microsoft.Sql/servers/databases",
      "apiVersion": "2023-08-01-preview",
      "name": "[format('{0}/{1}', parameters('sqlServerName'), parameters('sqlDatabaseName'))]",
      "location": "[parameters('location')]",
      "sku": {
        "name": "Basic",
        "tier": "Basic"
      },
      "properties": {
        "collation": "SQL_Latin1_General_CP1_CI_AS"
      },
      "dependsOn": [
        "[resourceId('Microsoft.Sql/servers', parameters('sqlServerName'))]"
      ]
    },
    {
      "type": "Microsoft.KeyVault/vaults/secrets",
      "apiVersion": "2023-07-01",
      "name": "[format('{0}/{1}', parameters('keyVaultName'), variables('sqlConnectionStringSecretName'))]",
      "properties": {
        "value": "[variables('sqlConnectionString')]"
      },
      "dependsOn": [
        "[resourceId('Microsoft.KeyVault/vaults', parameters('keyVaultName'))]",
        "[resourceId('Microsoft.Sql/servers/databases', parameters('sqlServerName'), parameters('sqlDatabaseName'))]",
        "[resourceId('Microsoft.Sql/servers', parameters('sqlServerName'))]"
      ]
    },
    {
      "type": "Microsoft.KeyVault/vaults/secrets",
      "apiVersion": "2023-07-01",
      "name": "[format('{0}/{1}', parameters('keyVaultName'), variables('jwtSecretSecretName'))]",
      "properties": {
        "value": "[parameters('jwtSecret')]"
      },
      "dependsOn": [
        "[resourceId('Microsoft.KeyVault/vaults', parameters('keyVaultName'))]"
      ]
    },
    {
      "type": "Microsoft.Web/serverfarms",
      "apiVersion": "2024-04-01",
      "name": "[parameters('appServicePlanName')]",
      "location": "[parameters('location')]",
      "sku": {
        "name": "B1",
        "tier": "Basic"
      },
      "kind": "linux",
      "properties": {
        "reserved": true
      }
    },
    {
      "type": "Microsoft.Web/sites",
      "apiVersion": "2024-04-01",
      "name": "[parameters('webAppName')]",
      "location": "[parameters('location')]",
      "kind": "app,linux",
      "identity": {
        "type": "SystemAssigned"
      },
      "properties": {
        "httpsOnly": true,
        "serverFarmId": "[resourceId('Microsoft.Web/serverfarms', parameters('appServicePlanName'))]",
        "siteConfig": {
          "appSettings": [
            {
              "name": "APPLICATIONINSIGHTS_CONNECTION_STRING",
              "value": "[reference(resourceId('Microsoft.Insights/components', parameters('applicationInsightsName')), '2020-02-02').ConnectionString]"
            },
            {
              "name": "Business__BusinessTimeZoneId",
              "value": "[parameters('businessTimeZoneId')]"
            },
            {
              "name": "ConnectionStrings__KinHub",
              "value": "[format('@Microsoft.KeyVault(VaultName={0};SecretName={1})', parameters('keyVaultName'), variables('sqlConnectionStringSecretName'))]"
            },
            {
              "name": "Jwt__Secret",
              "value": "[format('@Microsoft.KeyVault(VaultName={0};SecretName={1})', parameters('keyVaultName'), variables('jwtSecretSecretName'))]"
            },
            {
              "name": "Jwt__Issuer",
              "value": "[parameters('jwtIssuer')]"
            },
            {
              "name": "Jwt__AccessTokenExpiryMinutes",
              "value": "[parameters('jwtAccessTokenExpiryMinutes')]"
            }
          ],
          "ftpsState": "Disabled",
          "http20Enabled": true,
          "linuxFxVersion": "DOTNETCORE|8.0",
          "minTlsVersion": "1.2"
        }
      },
      "dependsOn": [
        "[resourceId('Microsoft.Insights/components', parameters('applicationInsightsName'))]",
        "[resourceId('Microsoft.Web/serverfarms', parameters('appServicePlanName'))]",
        "[resourceId('Microsoft.KeyVault/vaults', parameters('keyVaultName'))]"
      ]
    },
    {
      "type": "Microsoft.Authorization/roleAssignments",
      "apiVersion": "2022-04-01",
      "scope": "[resourceId('Microsoft.KeyVault/vaults', parameters('keyVaultName'))]",
      "name": "[guid(resourceId('Microsoft.KeyVault/vaults', parameters('keyVaultName')), resourceId('Microsoft.Web/sites', parameters('webAppName')), variables('keyVaultSecretsUserRoleDefinitionId'))]",
      "properties": {
        "principalId": "[reference(resourceId('Microsoft.Web/sites', parameters('webAppName')), '2024-04-01', 'full').identity.principalId]",
        "principalType": "ServicePrincipal",
        "roleDefinitionId": "[variables('keyVaultSecretsUserRoleDefinitionId')]"
      },
      "dependsOn": [
        "[resourceId('Microsoft.KeyVault/vaults', parameters('keyVaultName'))]",
        "[resourceId('Microsoft.Web/sites', parameters('webAppName'))]"
      ]
    },
    {
      "type": "Microsoft.Web/staticSites",
      "apiVersion": "2024-04-01",
      "name": "[parameters('staticWebAppName')]",
      "location": "[parameters('staticWebAppLocation')]",
      "sku": {
        "name": "Standard",
        "tier": "Standard"
      },
      "properties": {
        "allowConfigFileUpdates": true,
        "publicNetworkAccess": "Enabled",
        "stagingEnvironmentPolicy": "Disabled"
      }
    }
  ],
  "outputs": {
    "webAppDefaultHostname": {
      "type": "string",
      "value": "[reference(resourceId('Microsoft.Web/sites', parameters('webAppName')), '2024-04-01').defaultHostName]"
    },
    "staticWebAppDefaultHostname": {
      "type": "string",
      "value": "[reference(resourceId('Microsoft.Web/staticSites', parameters('staticWebAppName')), '2024-04-01').defaultHostname]"
    }
  }
}